fastuuid-0.13.3.dist-info/METADATA
fastuuid-0.13.3.dist-info/WHEEL
fastuuid-0.13.3.dist-info/licenses/LICENSE
fastuuid/__init__.py
fastuuid/__init__.pyi
fastuuid/fastuuid.cp38-win32.pyd
fastuuid/py.typed
fastuuid-0.13.3.dist-info/RECORD
