Metadata-Version: 2.4
Name: fastuuid
Version: 0.13.3
Classifier: Development Status :: 4 - Beta
Classifier: License :: OSI Approved :: BSD License
Classifier: Programming Language :: Rust
Classifier: Programming Language :: Python
Classifier: Programming Language :: Python :: 3 :: Only
Classifier: Programming Language :: Python :: 3
Classifier: Programming Language :: Python :: 3.8
Classifier: Programming Language :: Python :: 3.9
Classifier: Programming Language :: Python :: 3.10
Classifier: Programming Language :: Python :: 3.11
Classifier: Programming Language :: Python :: 3.12
Classifier: Programming Language :: Python :: 3.13
Classifier: Programming Language :: Python :: Implementation :: CPython
Classifier: Topic :: Software Development :: Libraries
Classifier: Topic :: Software Development :: Libraries :: Python Modules
License-File: LICENSE
Summary: Python bindings to Rust's UUID library.
Maintainer-email: Omer Katz <omer.drow@gmail.com>
Requires-Python: >=3.8
Project-URL: homepage, https://github.com/thedrow/fastuuid/
